example/__init__.py
shelf_reader/__init__.py
shelf_reader/compat.py
shelf_reader/mixins.py
shelf_reader/models.py
shelf_reader/shelf_reader.py
shelf_reader/ui.py
shelf_reader/utils.py
shelf_reader-0.1.dist-info/DESCRIPTION.rst
shelf_reader-0.1.dist-info/METADATA
shelf_reader-0.1.dist-info/RECORD
shelf_reader-0.1.dist-info/WHEEL
shelf_reader-0.1.dist-info/entry_points.txt
shelf_reader-0.1.dist-info/metadata.json
shelf_reader-0.1.dist-info/top_level.txt
tests/__init__.py
tests/test_callnumbers.py
tests/test_tokens.py
