Metadata-Version: 2.0
Name: shelf-reader
Version: 0.1
Summary: Make sure your collections are in call number order.
Home-page: https://github.com/asmacdo/shelf-reader
Author: Austin Macdonald
Author-email: asmacdo@gmail.com
License: GNU GENERAL PUBLIC LICENSE
